{"nodes": [{"id": "ER5215-301_DEV_resources_Guia_Vinculacion_STEP_GLB_EXCEL", "label": "Gu\u00eda de Vinculaci\u00f3n: STEP / GLB / EXCEL", "file_type": "document", "source_file": "ER5215-301_DEV/resources/Guia_Vinculacion_STEP_GLB_EXCEL.md", "source_location": null, "source_url": null, "captured_at": null, "author": null, "contributor": null}, {"id": "concept_step_file", "label": "STEP file (ISO-10303-21, AP214) \u2014 CAD source format", "file_type": "concept", "source_file": "ER5215-301_DEV/resources/Guia_Vinculacion_STEP_GLB_EXCEL.md", "source_location": null, "source_url": null, "captured_at": null, "author": null, "contributor": null}, {"id": "concept_glb_format", "label": "GLB format (glTF Binary) \u2014 3D visual model format", "file_type": "concept", "source_file": "ER5215-301_DEV/resources/Guia_Vinculacion_STEP_GLB_EXCEL.md", "source_location": null, "source_url": null, "captured_at": null, "author": null, "contributor": null}, {"id": "concept_excel_bom", "label": "Excel BOM \u2014 Flat material list (part_number, description, quantity)", "file_type": "concept", "source_file": "ER5215-301_DEV/resources/Guia_Vinculacion_STEP_GLB_EXCEL.md", "source_location": null, "source_url": null, "captured_at": null, "author": null, "contributor": null}, {"id": "concept_stemapping_isomorphism", "label": "STEP\u2194GLB Structural Isomorphism \u2014 Matching by child count (77 nodes)", "file_type": "concept", "source_file": "ER5215-301_DEV/resources/Guia_Vinculacion_STEP_GLB_EXCEL.md", "source_location": null, "source_url": null, "captured_at": null, "author": null, "contributor": null}, {"id": "concept_nauo", "label": "NAUO \u2014 NEXT_ASSEMBLY_USAGE_OCCURRENCE (STEP entity linking parent\u2194child)", "file_type": "concept", "source_file": "ER5215-301_DEV/resources/Guia_Vinculacion_STEP_GLB_EXCEL.md", "source_location": null, "source_url": null, "captured_at": null, "author": null, "contributor": null}, {"id": "rationale_step_as_linking_bridge", "label": "Design Rationale: STEP is the indispensable bridge linking GLB (NAUO#) to Excel (part_number)", "file_type": "rationale", "source_file": "ER5215-301_DEV/resources/Guia_Vinculacion_STEP_GLB_EXCEL.md", "source_location": null, "source_url": null, "captured_at": null, "author": null, "contributor": null}], "edges": [{"source": "ER5215-301_DEV_resources_Guia_Vinculacion_STEP_GLB_EXCEL", "target": "concept_step_file", "relation": "references", "confidence": "EXTRACTED", "confidence_score": 1.0, "source_file": "ER5215-301_DEV/resources/Guia_Vinculacion_STEP_GLB_EXCEL.md", "source_location": null, "weight": 1.0}, {"source": "ER5215-301_DEV_resources_Guia_Vinculacion_STEP_GLB_EXCEL", "target": "concept_glb_format", "relation": "references", "confidence": "EXTRACTED", "confidence_score": 1.0, "source_file": "ER5215-301_DEV/resources/Guia_Vinculacion_STEP_GLB_EXCEL.md", "source_location": null, "weight": 1.0}, {"source": "ER5215-301_DEV_resources_Guia_Vinculacion_STEP_GLB_EXCEL", "target": "concept_excel_bom", "relation": "references", "confidence": "EXTRACTED", "confidence_score": 1.0, "source_file": "ER5215-301_DEV/resources/Guia_Vinculacion_STEP_GLB_EXCEL.md", "source_location": null, "weight": 1.0}, {"source": "ER5215-301_DEV_resources_Guia_Vinculacion_STEP_GLB_EXCEL", "target": "concept_nauo", "relation": "references", "confidence": "EXTRACTED", "confidence_score": 1.0, "source_file": "ER5215-301_DEV/resources/Guia_Vinculacion_STEP_GLB_EXCEL.md", "source_location": null, "weight": 1.0}, {"source": "ER5215-301_DEV_resources_Guia_Vinculacion_STEP_GLB_EXCEL", "target": "concept_stemapping_isomorphism", "relation": "references", "confidence": "EXTRACTED", "confidence_score": 1.0, "source_file": "ER5215-301_DEV/resources/Guia_Vinculacion_STEP_GLB_EXCEL.md", "source_location": null, "weight": 1.0}, {"source": "concept_glb_format", "target": "concept_step_file", "relation": "conceptually_related_to", "confidence": "EXTRACTED", "confidence_score": 1.0, "source_file": "ER5215-301_DEV/resources/Guia_Vinculacion_STEP_GLB_EXCEL.md", "source_location": null, "weight": 1.0}, {"source": "concept_glb_format", "target": "concept_excel_bom", "relation": "conceptually_related_to", "confidence": "EXTRACTED", "confidence_score": 1.0, "source_file": "ER5215-301_DEV/resources/Guia_Vinculacion_STEP_GLB_EXCEL.md", "source_location": null, "weight": 1.0}, {"source": "concept_step_file", "target": "concept_excel_bom", "relation": "conceptually_related_to", "confidence": "EXTRACTED", "confidence_score": 1.0, "source_file": "ER5215-301_DEV/resources/Guia_Vinculacion_STEP_GLB_EXCEL.md", "source_location": null, "weight": 1.0}, {"source": "concept_nauo", "target": "concept_step_file", "relation": "conceptually_related_to", "confidence": "EXTRACTED", "confidence_score": 1.0, "source_file": "ER5215-301_DEV/resources/Guia_Vinculacion_STEP_GLB_EXCEL.md", "source_location": null, "weight": 1.0}, {"source": "concept_nauo", "target": "concept_glb_format", "relation": "conceptually_related_to", "confidence": "EXTRACTED", "confidence_score": 1.0, "source_file": "ER5215-301_DEV/resources/Guia_Vinculacion_STEP_GLB_EXCEL.md", "source_location": null, "weight": 1.0}, {"source": "concept_stemapping_isomorphism", "target": "concept_step_file", "relation": "conceptually_related_to", "confidence": "EXTRACTED", "confidence_score": 1.0, "source_file": "ER5215-301_DEV/resources/Guia_Vinculacion_STEP_GLB_EXCEL.md", "source_location": null, "weight": 1.0}, {"source": "concept_stemapping_isomorphism", "target": "concept_glb_format", "relation": "conceptually_related_to", "confidence": "EXTRACTED", "confidence_score": 1.0, "source_file": "ER5215-301_DEV/resources/Guia_Vinculacion_STEP_GLB_EXCEL.md", "source_location": null, "weight": 1.0}, {"source": "rationale_step_as_linking_bridge", "target": "concept_stemapping_isomorphism", "relation": "rationale_for", "confidence": "EXTRACTED", "confidence_score": 1.0, "source_file": "ER5215-301_DEV/resources/Guia_Vinculacion_STEP_GLB_EXCEL.md", "source_location": null, "weight": 1.0}, {"source": "rationale_step_as_linking_bridge", "target": "concept_step_file", "relation": "rationale_for", "confidence": "EXTRACTED", "confidence_score": 1.0, "source_file": "ER5215-301_DEV/resources/Guia_Vinculacion_STEP_GLB_EXCEL.md", "source_location": null, "weight": 1.0}, {"source": "ER5215-301_DEV_resources_Guia_Vinculacion_STEP_GLB_EXCEL", "target": "concept_er5215_301", "relation": "references", "confidence": "EXTRACTED", "confidence_score": 1.0, "source_file": "ER5215-301_DEV/resources/Guia_Vinculacion_STEP_GLB_EXCEL.md", "source_location": null, "weight": 1.0}], "hyperedges": []}